{
  "last_updated": "2025-11-27T06:57:30.535224",
  "total_stocks_analyzed": 18,
  "data_sources": {
    "alphavantage": 18
  },
  "stocks": [
    {
      "ticker": "LLOY.L",
      "current_price": 93.8,
      "price_change": 3.12,
      "price_change_percent": 3.44,
      "volume": 237527772,
      "volume_ratio": 1.0,
      "company_name": "Lloyds Banking Group",
      "confidence_score": 70,
      "analysis": "\ud83d\udcc8 Positive trend developing with significant price movement volume below average",
      "catalyst": "Alpha Vantage API data",
      "data_source": "alphavantage",
      "last_updated": "2025-11-27T06:57:10.026562",
      "region": "UK"
    },
    {
      "ticker": "BARC.L",
      "current_price": 422.95,
      "price_change": 12.95,
      "price_change_percent": 3.16,
      "volume": 35516804,
      "volume_ratio": 1.0,
      "company_name": "Barclays PLC",
      "confidence_score": 70,
      "analysis": "\ud83d\udcc8 Positive trend developing with significant price movement volume below average",
      "catalyst": "Alpha Vantage API data",
      "data_source": "alphavantage",
      "last_updated": "2025-11-27T06:57:16.363203",
      "region": "UK"
    },
    {
      "ticker": "ASML.AS",
      "current_price": 909.3,
      "price_change": 49.0,
      "price_change_percent": 5.7,
      "volume": 684564,
      "volume_ratio": 1.0,
      "company_name": "ASML Holding NV",
      "confidence_score": 70,
      "analysis": "\ud83d\udcc8 Positive trend developing with significant price movement volume below average",
      "catalyst": "Alpha Vantage API data",
      "data_source": "alphavantage",
      "last_updated": "2025-11-27T06:57:24.524093",
      "region": "EU"
    },
    {
      "ticker": "MSFT",
      "current_price": 485.5,
      "price_change": 8.51,
      "price_change_percent": 1.78,
      "volume": 25709079,
      "volume_ratio": 1.0,
      "company_name": "Microsoft Corporation",
      "confidence_score": 62,
      "analysis": "\ud83d\udcc8 Positive trend developing with positive price action volume below average",
      "catalyst": "Alpha Vantage API data",
      "data_source": "alphavantage",
      "last_updated": "2025-11-27T06:56:38.589474",
      "region": "US"
    },
    {
      "ticker": "TSLA",
      "current_price": 426.58,
      "price_change": 7.18,
      "price_change_percent": 1.71,
      "volume": 62539506,
      "volume_ratio": 1.0,
      "company_name": "Tesla Inc.",
      "confidence_score": 62,
      "analysis": "\ud83d\udcc8 Positive trend developing with positive price action volume below average",
      "catalyst": "Alpha Vantage API data",
      "data_source": "alphavantage",
      "last_updated": "2025-11-27T06:56:42.779820",
      "region": "US"
    },
    {
      "ticker": "NVDA",
      "current_price": 180.26,
      "price_change": 2.44,
      "price_change_percent": 1.37,
      "volume": 182061197,
      "volume_ratio": 1.0,
      "company_name": "NVIDIA Corporation",
      "confidence_score": 62,
      "analysis": "\ud83d\udcc8 Positive trend developing with positive price action volume below average",
      "catalyst": "Alpha Vantage API data",
      "data_source": "alphavantage",
      "last_updated": "2025-11-27T06:56:45.057943",
      "region": "US"
    },
    {
      "ticker": "NFLX",
      "current_price": 106.14,
      "price_change": 1.74,
      "price_change_percent": 1.67,
      "volume": 27861030,
      "volume_ratio": 1.0,
      "company_name": "Netflix Inc.",
      "confidence_score": 62,
      "analysis": "\ud83d\udcc8 Positive trend developing with positive price action volume below average",
      "catalyst": "Alpha Vantage API data",
      "data_source": "alphavantage",
      "last_updated": "2025-11-27T06:57:02.684396",
      "region": "US"
    },
    {
      "ticker": "TSCO.L",
      "current_price": 453.4,
      "price_change": 8.3,
      "price_change_percent": 1.86,
      "volume": 13948239,
      "volume_ratio": 1.0,
      "company_name": "Tesco PLC",
      "confidence_score": 62,
      "analysis": "\ud83d\udcc8 Positive trend developing with positive price action volume below average",
      "catalyst": "Alpha Vantage API data",
      "data_source": "alphavantage",
      "last_updated": "2025-11-27T06:57:02.929920",
      "region": "UK"
    },
    {
      "ticker": "HSBA.L",
      "current_price": 1064.4,
      "price_change": 13.8,
      "price_change_percent": 1.31,
      "volume": 31251661,
      "volume_ratio": 1.0,
      "company_name": "HSBC Holdings PLC",
      "confidence_score": 62,
      "analysis": "\ud83d\udcc8 Positive trend developing with positive price action volume below average",
      "catalyst": "Alpha Vantage API data",
      "data_source": "alphavantage",
      "last_updated": "2025-11-27T06:57:07.495987",
      "region": "UK"
    },
    {
      "ticker": "VOD.L",
      "current_price": 94.08,
      "price_change": 1.56,
      "price_change_percent": 1.69,
      "volume": 124768261,
      "volume_ratio": 1.0,
      "company_name": "Vodafone Group PLC",
      "confidence_score": 62,
      "analysis": "\ud83d\udcc8 Positive trend developing with positive price action volume below average",
      "catalyst": "Alpha Vantage API data",
      "data_source": "alphavantage",
      "last_updated": "2025-11-27T06:57:14.047407",
      "region": "UK"
    },
    {
      "ticker": "AIR.PA",
      "current_price": 204.85,
      "price_change": 3.1,
      "price_change_percent": 1.54,
      "volume": 680047,
      "volume_ratio": 1.0,
      "company_name": "Airbus SE",
      "confidence_score": 62,
      "analysis": "\ud83d\udcc8 Positive trend developing with positive price action volume below average",
      "catalyst": "Alpha Vantage API data",
      "data_source": "alphavantage",
      "last_updated": "2025-11-27T06:57:16.626802",
      "region": "EU"
    },
    {
      "ticker": "AAPL",
      "current_price": 277.55,
      "price_change": 0.58,
      "price_change_percent": 0.21,
      "volume": 33431423,
      "volume_ratio": 1.0,
      "company_name": "Apple Inc.",
      "confidence_score": 56,
      "analysis": "\u26a1 Watch for confirmation with positive price action volume below average",
      "catalyst": "Alpha Vantage API data",
      "data_source": "alphavantage",
      "last_updated": "2025-11-27T06:56:33.676550",
      "region": "US"
    },
    {
      "ticker": "SIE.DE",
      "current_price": 228.1,
      "price_change": 1.1,
      "price_change_percent": 0.48,
      "volume": 689041,
      "volume_ratio": 1.0,
      "company_name": "Siemens AG",
      "confidence_score": 56,
      "analysis": "\u26a1 Watch for confirmation with positive price action volume below average",
      "catalyst": "Alpha Vantage API data",
      "data_source": "alphavantage",
      "last_updated": "2025-11-27T06:57:20.544403",
      "region": "EU"
    },
    {
      "ticker": "SAF.PA",
      "current_price": 289.1,
      "price_change": 2.8,
      "price_change_percent": 0.98,
      "volume": 424075,
      "volume_ratio": 1.0,
      "company_name": "Safran SA",
      "confidence_score": 56,
      "analysis": "\u26a1 Watch for confirmation with positive price action volume below average",
      "catalyst": "Alpha Vantage API data",
      "data_source": "alphavantage",
      "last_updated": "2025-11-27T06:57:27.430462",
      "region": "EU"
    },
    {
      "ticker": "GOOGL",
      "current_price": 319.95,
      "price_change": -3.49,
      "price_change_percent": -1.08,
      "volume": 51373361,
      "volume_ratio": 1.0,
      "company_name": "Alphabet Inc.",
      "confidence_score": 50,
      "analysis": "\u26a1 Watch for confirmation consolidating at current levels volume below average",
      "catalyst": "Alpha Vantage API data",
      "data_source": "alphavantage",
      "last_updated": "2025-11-27T06:56:50.123578",
      "region": "US"
    },
    {
      "ticker": "META",
      "current_price": 633.61,
      "price_change": -2.61,
      "price_change_percent": -0.41,
      "volume": 14484995,
      "volume_ratio": 1.0,
      "company_name": "Meta Platforms Inc.",
      "confidence_score": 50,
      "analysis": "\u26a1 Watch for confirmation consolidating at current levels volume below average",
      "catalyst": "Alpha Vantage API data",
      "data_source": "alphavantage",
      "last_updated": "2025-11-27T06:56:54.699970",
      "region": "US"
    },
    {
      "ticker": "AMZN",
      "current_price": 229.16,
      "price_change": -0.51,
      "price_change_percent": -0.22,
      "volume": 38497922,
      "volume_ratio": 1.0,
      "company_name": "Amazon.com Inc.",
      "confidence_score": 50,
      "analysis": "\u26a1 Watch for confirmation consolidating at current levels volume below average",
      "catalyst": "Alpha Vantage API data",
      "data_source": "alphavantage",
      "last_updated": "2025-11-27T06:56:57.448800",
      "region": "US"
    },
    {
      "ticker": "BMW.DE",
      "current_price": 87.4,
      "price_change": -0.24,
      "price_change_percent": -0.27,
      "volume": 515763,
      "volume_ratio": 1.0,
      "company_name": "BMW AG",
      "confidence_score": 50,
      "analysis": "\u26a1 Watch for confirmation consolidating at current levels volume below average",
      "catalyst": "Alpha Vantage API data",
      "data_source": "alphavantage",
      "last_updated": "2025-11-27T06:57:30.534303",
      "region": "EU"
    }
  ]
}