{
  "last_updated": "2026-04-02T07:08:55.316907",
  "total_stocks_analyzed": 18,
  "data_sources": {
    "alphavantage": 16,
    "sample": 2
  },
  "stocks": [
    {
      "ticker": "GOOGL",
      "current_price": 297.39,
      "price_change": 9.83,
      "price_change_percent": 3.42,
      "volume": 37440669,
      "volume_ratio": 1.0,
      "company_name": "Alphabet Inc.",
      "confidence_score": 70,
      "analysis": "\ud83d\udcc8 Positive trend developing with significant price movement volume below average",
      "catalyst": "Alpha Vantage API data",
      "data_source": "alphavantage",
      "last_updated": "2026-04-02T07:08:16.606768",
      "region": "US"
    },
    {
      "ticker": "HSBA.L",
      "current_price": 1286.6,
      "price_change": 65.0,
      "price_change_percent": 5.32,
      "volume": 37195149,
      "volume_ratio": 1.0,
      "company_name": "HSBC Holdings PLC",
      "confidence_score": 70,
      "analysis": "\ud83d\udcc8 Positive trend developing with significant price movement volume below average",
      "catalyst": "Alpha Vantage API data",
      "data_source": "alphavantage",
      "last_updated": "2026-04-02T07:08:29.066762",
      "region": "UK"
    },
    {
      "ticker": "LLOY.L",
      "current_price": 97.7,
      "price_change": 5.36,
      "price_change_percent": 5.8,
      "volume": 270978703,
      "volume_ratio": 1.0,
      "company_name": "Lloyds Banking Group",
      "confidence_score": 70,
      "analysis": "\ud83d\udcc8 Positive trend developing with significant price movement volume below average",
      "catalyst": "Alpha Vantage API data",
      "data_source": "alphavantage",
      "last_updated": "2026-04-02T07:08:31.556681",
      "region": "UK"
    },
    {
      "ticker": "BARC.L",
      "current_price": 409.1,
      "price_change": 19.65,
      "price_change_percent": 5.05,
      "volume": 56249961,
      "volume_ratio": 1.0,
      "company_name": "Barclays PLC",
      "confidence_score": 70,
      "analysis": "\ud83d\udcc8 Positive trend developing with significant price movement volume below average",
      "catalyst": "Alpha Vantage API data",
      "data_source": "alphavantage",
      "last_updated": "2026-04-02T07:08:38.194550",
      "region": "UK"
    },
    {
      "ticker": "SIE.DE",
      "current_price": 215.35,
      "price_change": 9.65,
      "price_change_percent": 4.69,
      "volume": 1792047,
      "volume_ratio": 1.0,
      "company_name": "Siemens AG",
      "confidence_score": 70,
      "analysis": "\ud83d\udcc8 Positive trend developing with significant price movement volume below average",
      "catalyst": "Alpha Vantage API data",
      "data_source": "alphavantage",
      "last_updated": "2026-04-02T07:08:42.863449",
      "region": "EU"
    },
    {
      "ticker": "ASML.AS",
      "current_price": 1187.6,
      "price_change": 68.4,
      "price_change_percent": 6.11,
      "volume": 741501,
      "volume_ratio": 1.0,
      "company_name": "ASML Holding NV",
      "confidence_score": 70,
      "analysis": "\ud83d\udcc8 Positive trend developing with significant price movement volume below average",
      "catalyst": "Alpha Vantage API data",
      "data_source": "alphavantage",
      "last_updated": "2026-04-02T07:08:47.951197",
      "region": "EU"
    },
    {
      "ticker": "SAF.PA",
      "current_price": 290.6,
      "price_change": 11.2,
      "price_change_percent": 4.01,
      "volume": 845138,
      "volume_ratio": 1.0,
      "company_name": "Safran SA",
      "confidence_score": 70,
      "analysis": "\ud83d\udcc8 Positive trend developing with significant price movement volume below average",
      "catalyst": "Alpha Vantage API data",
      "data_source": "alphavantage",
      "last_updated": "2026-04-02T07:08:51.176229",
      "region": "EU"
    },
    {
      "ticker": "TSLA",
      "current_price": 381.26,
      "price_change": 9.51,
      "price_change_percent": 2.56,
      "volume": 58683752,
      "volume_ratio": 1.0,
      "company_name": "Tesla Inc.",
      "confidence_score": 62,
      "analysis": "\ud83d\udcc8 Positive trend developing with significant price movement volume below average",
      "catalyst": "Alpha Vantage API data",
      "data_source": "alphavantage",
      "last_updated": "2026-04-02T07:08:09.725036",
      "region": "US"
    },
    {
      "ticker": "META",
      "current_price": 579.23,
      "price_change": 7.1,
      "price_change_percent": 1.24,
      "volume": 23608128,
      "volume_ratio": 1.0,
      "company_name": "Meta Platforms Inc.",
      "confidence_score": 62,
      "analysis": "\ud83d\udcc8 Positive trend developing with positive price action volume below average",
      "catalyst": "Alpha Vantage API data",
      "data_source": "alphavantage",
      "last_updated": "2026-04-02T07:08:19.189041",
      "region": "US"
    },
    {
      "ticker": "AMZN",
      "current_price": 210.57,
      "price_change": 2.3,
      "price_change_percent": 1.1,
      "volume": 45955395,
      "volume_ratio": 1.0,
      "company_name": "Amazon.com Inc.",
      "confidence_score": 62,
      "analysis": "\ud83d\udcc8 Positive trend developing with positive price action volume below average",
      "catalyst": "Alpha Vantage API data",
      "data_source": "alphavantage",
      "last_updated": "2026-04-02T07:08:21.790206",
      "region": "US"
    },
    {
      "ticker": "BMW.DE",
      "current_price": 79.02,
      "price_change": 1.02,
      "price_change_percent": 1.31,
      "volume": 964952,
      "volume_ratio": 1.0,
      "company_name": "BMW AG",
      "confidence_score": 62,
      "analysis": "\ud83d\udcc8 Positive trend developing with positive price action volume below average",
      "catalyst": "Alpha Vantage API data",
      "data_source": "alphavantage",
      "last_updated": "2026-04-02T07:08:55.316299",
      "region": "EU"
    },
    {
      "ticker": "AAPL",
      "current_price": 255.63,
      "price_change": 1.84,
      "price_change_percent": 0.73,
      "volume": 40059432,
      "volume_ratio": 1.0,
      "company_name": "Apple Inc.",
      "confidence_score": 56,
      "analysis": "\u26a1 Watch for confirmation with positive price action volume below average",
      "catalyst": "Alpha Vantage API data",
      "data_source": "alphavantage",
      "last_updated": "2026-04-02T07:08:01.451241",
      "region": "US"
    },
    {
      "ticker": "NVDA",
      "current_price": 175.75,
      "price_change": 1.35,
      "price_change_percent": 0.77,
      "volume": 168132005,
      "volume_ratio": 1.0,
      "company_name": "NVIDIA Corporation",
      "confidence_score": 56,
      "analysis": "\u26a1 Watch for confirmation with positive price action volume below average",
      "catalyst": "Alpha Vantage API data",
      "data_source": "alphavantage",
      "last_updated": "2026-04-02T07:08:12.164139",
      "region": "US"
    },
    {
      "ticker": "VOD.L",
      "current_price": 113.65,
      "price_change": 0.35,
      "price_change_percent": 0.31,
      "volume": 62998393,
      "volume_ratio": 1.0,
      "company_name": "Vodafone Group PLC",
      "confidence_score": 56,
      "analysis": "\u26a1 Watch for confirmation with positive price action volume below average",
      "catalyst": "Alpha Vantage API data",
      "data_source": "alphavantage",
      "last_updated": "2026-04-02T07:08:35.175028",
      "region": "UK"
    },
    {
      "ticker": "MSFT",
      "current_price": 369.37,
      "price_change": -0.8,
      "price_change_percent": -0.22,
      "volume": 29417206,
      "volume_ratio": 1.0,
      "company_name": "Microsoft Corporation",
      "confidence_score": 50,
      "analysis": "\u26a1 Watch for confirmation consolidating at current levels volume below average",
      "catalyst": "Alpha Vantage API data",
      "data_source": "alphavantage",
      "last_updated": "2026-04-02T07:08:05.906869",
      "region": "US"
    },
    {
      "ticker": "NFLX",
      "current_price": 95.55,
      "price_change": -0.6,
      "price_change_percent": -0.62,
      "volume": 30439305,
      "volume_ratio": 1.0,
      "company_name": "Netflix Inc.",
      "confidence_score": 50,
      "analysis": "\u26a1 Watch for confirmation consolidating at current levels volume below average",
      "catalyst": "Alpha Vantage API data",
      "data_source": "alphavantage",
      "last_updated": "2026-04-02T07:08:24.434801",
      "region": "US"
    },
    {
      "ticker": "TSCO.L",
      "current_price": 2.87,
      "price_change": -0.01,
      "price_change_percent": -0.36,
      "volume": 38253626,
      "volume_ratio": 0.89,
      "company_name": "Tesco PLC",
      "confidence_score": 47,
      "analysis": "\u26a1 Watch for confirmation consolidating at current levels volume below average",
      "catalyst": "Sample data - API limited",
      "data_source": "sample",
      "last_updated": "2026-04-02T07:08:24.616551",
      "region": "UK"
    },
    {
      "ticker": "AIR.PA",
      "current_price": 140.59,
      "price_change": 2.27,
      "price_change_percent": 1.64,
      "volume": 7309037,
      "volume_ratio": 1.37,
      "company_name": "Airbus SE",
      "confidence_score": 47,
      "analysis": "\u26a1 Watch for confirmation with positive price action on average volume",
      "catalyst": "Sample data - API limited",
      "data_source": "sample",
      "last_updated": "2026-04-02T07:08:38.381466",
      "region": "EU"
    }
  ]
}