{
  "last_updated": "2026-03-16T07:13:24.162315",
  "total_stocks_analyzed": 18,
  "data_sources": {
    "sample": 2,
    "alphavantage": 16
  },
  "stocks": [
    {
      "ticker": "TSCO.L",
      "current_price": 2.99,
      "price_change": 0.05,
      "price_change_percent": 1.57,
      "volume": 4678074,
      "volume_ratio": 2.18,
      "company_name": "Tesco PLC",
      "confidence_score": 69,
      "analysis": "\ud83d\udcc8 Positive trend developing with positive price action on high volume",
      "catalyst": "Sample data - API limited",
      "data_source": "sample",
      "last_updated": "2026-03-16T07:12:56.730884",
      "region": "UK"
    },
    {
      "ticker": "NFLX",
      "current_price": 95.31,
      "price_change": 1.0,
      "price_change_percent": 1.06,
      "volume": 29876659,
      "volume_ratio": 1.0,
      "company_name": "Netflix Inc.",
      "confidence_score": 62,
      "analysis": "\ud83d\udcc8 Positive trend developing with positive price action volume below average",
      "catalyst": "Alpha Vantage API data",
      "data_source": "alphavantage",
      "last_updated": "2026-03-16T07:12:56.478317",
      "region": "US"
    },
    {
      "ticker": "VOD.L",
      "current_price": 109.2,
      "price_change": 1.4,
      "price_change_percent": 1.3,
      "volume": 38756690,
      "volume_ratio": 1.0,
      "company_name": "Vodafone Group PLC",
      "confidence_score": 62,
      "analysis": "\ud83d\udcc8 Positive trend developing with positive price action volume below average",
      "catalyst": "Alpha Vantage API data",
      "data_source": "alphavantage",
      "last_updated": "2026-03-16T07:13:06.082759",
      "region": "UK"
    },
    {
      "ticker": "AIR.PA",
      "current_price": 160.12,
      "price_change": 6.21,
      "price_change_percent": 4.03,
      "volume": 49984282,
      "volume_ratio": 1.37,
      "company_name": "Airbus SE",
      "confidence_score": 57,
      "analysis": "\u26a1 Watch for confirmation with significant price movement on average volume",
      "catalyst": "Sample data - API limited",
      "data_source": "sample",
      "last_updated": "2026-03-16T07:13:10.541768",
      "region": "EU"
    },
    {
      "ticker": "MSFT",
      "current_price": 395.55,
      "price_change": -6.31,
      "price_change_percent": -1.57,
      "volume": 26848000,
      "volume_ratio": 1.0,
      "company_name": "Microsoft Corporation",
      "confidence_score": 50,
      "analysis": "\u26a1 Watch for confirmation consolidating at current levels volume below average",
      "catalyst": "Alpha Vantage API data",
      "data_source": "alphavantage",
      "last_updated": "2026-03-16T07:12:34.074640",
      "region": "US"
    },
    {
      "ticker": "TSLA",
      "current_price": 391.2,
      "price_change": -3.81,
      "price_change_percent": -0.96,
      "volume": 58504091,
      "volume_ratio": 1.0,
      "company_name": "Tesla Inc.",
      "confidence_score": 50,
      "analysis": "\u26a1 Watch for confirmation consolidating at current levels volume below average",
      "catalyst": "Alpha Vantage API data",
      "data_source": "alphavantage",
      "last_updated": "2026-03-16T07:12:36.960811",
      "region": "US"
    },
    {
      "ticker": "NVDA",
      "current_price": 180.25,
      "price_change": -2.89,
      "price_change_percent": -1.58,
      "volume": 160988424,
      "volume_ratio": 1.0,
      "company_name": "NVIDIA Corporation",
      "confidence_score": 50,
      "analysis": "\u26a1 Watch for confirmation consolidating at current levels volume below average",
      "catalyst": "Alpha Vantage API data",
      "data_source": "alphavantage",
      "last_updated": "2026-03-16T07:12:40.291780",
      "region": "US"
    },
    {
      "ticker": "GOOGL",
      "current_price": 302.28,
      "price_change": -1.27,
      "price_change_percent": -0.42,
      "volume": 23693092,
      "volume_ratio": 1.0,
      "company_name": "Alphabet Inc.",
      "confidence_score": 50,
      "analysis": "\u26a1 Watch for confirmation consolidating at current levels volume below average",
      "catalyst": "Alpha Vantage API data",
      "data_source": "alphavantage",
      "last_updated": "2026-03-16T07:12:44.909043",
      "region": "US"
    },
    {
      "ticker": "AMZN",
      "current_price": 207.67,
      "price_change": -1.86,
      "price_change_percent": -0.89,
      "volume": 35662137,
      "volume_ratio": 1.0,
      "company_name": "Amazon.com Inc.",
      "confidence_score": 50,
      "analysis": "\u26a1 Watch for confirmation consolidating at current levels volume below average",
      "catalyst": "Alpha Vantage API data",
      "data_source": "alphavantage",
      "last_updated": "2026-03-16T07:12:53.142404",
      "region": "US"
    },
    {
      "ticker": "HSBA.L",
      "current_price": 1180.4,
      "price_change": -15.4,
      "price_change_percent": -1.29,
      "volume": 53302156,
      "volume_ratio": 1.0,
      "company_name": "HSBC Holdings PLC",
      "confidence_score": 50,
      "analysis": "\u26a1 Watch for confirmation consolidating at current levels volume below average",
      "catalyst": "Alpha Vantage API data",
      "data_source": "alphavantage",
      "last_updated": "2026-03-16T07:12:59.006760",
      "region": "UK"
    },
    {
      "ticker": "LLOY.L",
      "current_price": 94.18,
      "price_change": -1.32,
      "price_change_percent": -1.38,
      "volume": 105182468,
      "volume_ratio": 1.0,
      "company_name": "Lloyds Banking Group",
      "confidence_score": 50,
      "analysis": "\u26a1 Watch for confirmation consolidating at current levels volume below average",
      "catalyst": "Alpha Vantage API data",
      "data_source": "alphavantage",
      "last_updated": "2026-03-16T07:13:02.922104",
      "region": "UK"
    },
    {
      "ticker": "BARC.L",
      "current_price": 386.25,
      "price_change": -3.1,
      "price_change_percent": -0.8,
      "volume": 47542534,
      "volume_ratio": 1.0,
      "company_name": "Barclays PLC",
      "confidence_score": 50,
      "analysis": "\u26a1 Watch for confirmation consolidating at current levels volume below average",
      "catalyst": "Alpha Vantage API data",
      "data_source": "alphavantage",
      "last_updated": "2026-03-16T07:13:10.301651",
      "region": "UK"
    },
    {
      "ticker": "SIE.DE",
      "current_price": 220.35,
      "price_change": -4.35,
      "price_change_percent": -1.94,
      "volume": 1015432,
      "volume_ratio": 1.0,
      "company_name": "Siemens AG",
      "confidence_score": 50,
      "analysis": "\u26a1 Watch for confirmation consolidating at current levels volume below average",
      "catalyst": "Alpha Vantage API data",
      "data_source": "alphavantage",
      "last_updated": "2026-03-16T07:13:13.593642",
      "region": "EU"
    },
    {
      "ticker": "ASML.AS",
      "current_price": 1179.6,
      "price_change": -0.8,
      "price_change_percent": -0.07,
      "volume": 478619,
      "volume_ratio": 1.0,
      "company_name": "ASML Holding NV",
      "confidence_score": 50,
      "analysis": "\u26a1 Watch for confirmation consolidating at current levels volume below average",
      "catalyst": "Alpha Vantage API data",
      "data_source": "alphavantage",
      "last_updated": "2026-03-16T07:13:17.152602",
      "region": "EU"
    },
    {
      "ticker": "SAF.PA",
      "current_price": 304.4,
      "price_change": -3.7,
      "price_change_percent": -1.2,
      "volume": 556080,
      "volume_ratio": 1.0,
      "company_name": "Safran SA",
      "confidence_score": 50,
      "analysis": "\u26a1 Watch for confirmation consolidating at current levels volume below average",
      "catalyst": "Alpha Vantage API data",
      "data_source": "alphavantage",
      "last_updated": "2026-03-16T07:13:20.925437",
      "region": "EU"
    },
    {
      "ticker": "BMW.DE",
      "current_price": 81.3,
      "price_change": -0.38,
      "price_change_percent": -0.47,
      "volume": 1181090,
      "volume_ratio": 1.0,
      "company_name": "BMW AG",
      "confidence_score": 50,
      "analysis": "\u26a1 Watch for confirmation consolidating at current levels volume below average",
      "catalyst": "Alpha Vantage API data",
      "data_source": "alphavantage",
      "last_updated": "2026-03-16T07:13:24.161378",
      "region": "EU"
    },
    {
      "ticker": "AAPL",
      "current_price": 250.12,
      "price_change": -5.64,
      "price_change_percent": -2.21,
      "volume": 36929988,
      "volume_ratio": 1.0,
      "company_name": "Apple Inc.",
      "confidence_score": 40,
      "analysis": "\ud83d\udd04 Needs stronger signals consolidating at current levels volume below average",
      "catalyst": "Alpha Vantage API data",
      "data_source": "alphavantage",
      "last_updated": "2026-03-16T07:12:30.186884",
      "region": "US"
    },
    {
      "ticker": "META",
      "current_price": 613.71,
      "price_change": -24.47,
      "price_change_percent": -3.83,
      "volume": 18957637,
      "volume_ratio": 1.0,
      "company_name": "Meta Platforms Inc.",
      "confidence_score": 40,
      "analysis": "\ud83d\udd04 Needs stronger signals consolidating at current levels volume below average",
      "catalyst": "Alpha Vantage API data",
      "data_source": "alphavantage",
      "last_updated": "2026-03-16T07:12:48.590059",
      "region": "US"
    }
  ]
}