{
  "last_updated": "2025-12-22T06:31:39.321974",
  "total_stocks_analyzed": 18,
  "data_sources": {
    "sample": 8,
    "alphavantage": 10
  },
  "stocks": [
    {
      "ticker": "TSCO.L",
      "current_price": 2.98,
      "price_change": -0.04,
      "price_change_percent": -1.41,
      "volume": 1788552,
      "volume_ratio": 1.06,
      "company_name": "Tesco PLC",
      "confidence_score": 81,
      "analysis": "\ud83d\ude80 Strong bullish momentum consolidating at current levels on average volume",
      "catalyst": "Sample data - API limited",
      "data_source": "sample",
      "last_updated": "2025-12-22T06:31:06.007306",
      "region": "UK"
    },
    {
      "ticker": "NVDA",
      "current_price": 180.99,
      "price_change": 6.85,
      "price_change_percent": 3.93,
      "volume": 324925927,
      "volume_ratio": 1.0,
      "company_name": "NVIDIA Corporation",
      "confidence_score": 70,
      "analysis": "\ud83d\udcc8 Positive trend developing with significant price movement volume below average",
      "catalyst": "Alpha Vantage API data",
      "data_source": "alphavantage",
      "last_updated": "2025-12-22T06:30:51.212484",
      "region": "US"
    },
    {
      "ticker": "GOOGL",
      "current_price": 307.16,
      "price_change": 4.7,
      "price_change_percent": 1.55,
      "volume": 59943239,
      "volume_ratio": 1.0,
      "company_name": "Alphabet Inc.",
      "confidence_score": 62,
      "analysis": "\ud83d\udcc8 Positive trend developing with positive price action volume below average",
      "catalyst": "Alpha Vantage API data",
      "data_source": "alphavantage",
      "last_updated": "2025-12-22T06:30:55.397866",
      "region": "US"
    },
    {
      "ticker": "HSBA.L",
      "current_price": 1167.0,
      "price_change": 16.6,
      "price_change_percent": 1.44,
      "volume": 67933739,
      "volume_ratio": 1.0,
      "company_name": "HSBC Holdings PLC",
      "confidence_score": 62,
      "analysis": "\ud83d\udcc8 Positive trend developing with positive price action volume below average",
      "catalyst": "Alpha Vantage API data",
      "data_source": "alphavantage",
      "last_updated": "2025-12-22T06:31:09.567150",
      "region": "UK"
    },
    {
      "ticker": "LLOY.L",
      "current_price": 97.42,
      "price_change": 1.08,
      "price_change_percent": 1.12,
      "volume": 331403071,
      "volume_ratio": 1.0,
      "company_name": "Lloyds Banking Group",
      "confidence_score": 62,
      "analysis": "\ud83d\udcc8 Positive trend developing with positive price action volume below average",
      "catalyst": "Alpha Vantage API data",
      "data_source": "alphavantage",
      "last_updated": "2025-12-22T06:31:14.374889",
      "region": "UK"
    },
    {
      "ticker": "BARC.L",
      "current_price": 1.69,
      "price_change": -0.03,
      "price_change_percent": -1.63,
      "volume": 3816696,
      "volume_ratio": 1.1,
      "company_name": "Barclays PLC",
      "confidence_score": 60,
      "analysis": "\ud83d\udcc8 Positive trend developing consolidating at current levels on average volume",
      "catalyst": "Sample data - API limited",
      "data_source": "sample",
      "last_updated": "2025-12-22T06:31:22.012915",
      "region": "UK"
    },
    {
      "ticker": "SAF.PA",
      "current_price": 221.35,
      "price_change": 10.19,
      "price_change_percent": 4.82,
      "volume": 48582574,
      "volume_ratio": 1.68,
      "company_name": "Safran SA",
      "confidence_score": 59,
      "analysis": "\u26a1 Watch for confirmation with significant price movement on high volume",
      "catalyst": "Sample data - API limited",
      "data_source": "sample",
      "last_updated": "2025-12-22T06:31:34.623577",
      "region": "EU"
    },
    {
      "ticker": "AIR.PA",
      "current_price": 139.5,
      "price_change": -1.18,
      "price_change_percent": -0.84,
      "volume": 45947055,
      "volume_ratio": 2.12,
      "company_name": "Airbus SE",
      "confidence_score": 58,
      "analysis": "\u26a1 Watch for confirmation consolidating at current levels on high volume",
      "catalyst": "Sample data - API limited",
      "data_source": "sample",
      "last_updated": "2025-12-22T06:31:22.248021",
      "region": "EU"
    },
    {
      "ticker": "AAPL",
      "current_price": 273.67,
      "price_change": 1.48,
      "price_change_percent": 0.54,
      "volume": 144632048,
      "volume_ratio": 1.0,
      "company_name": "Apple Inc.",
      "confidence_score": 56,
      "analysis": "\u26a1 Watch for confirmation with positive price action volume below average",
      "catalyst": "Alpha Vantage API data",
      "data_source": "alphavantage",
      "last_updated": "2025-12-22T06:30:39.436020",
      "region": "US"
    },
    {
      "ticker": "MSFT",
      "current_price": 485.92,
      "price_change": 1.94,
      "price_change_percent": 0.4,
      "volume": 70836105,
      "volume_ratio": 1.0,
      "company_name": "Microsoft Corporation",
      "confidence_score": 56,
      "analysis": "\u26a1 Watch for confirmation with positive price action volume below average",
      "catalyst": "Alpha Vantage API data",
      "data_source": "alphavantage",
      "last_updated": "2025-12-22T06:30:44.142725",
      "region": "US"
    },
    {
      "ticker": "AMZN",
      "current_price": 227.35,
      "price_change": 0.59,
      "price_change_percent": 0.26,
      "volume": 85544374,
      "volume_ratio": 1.0,
      "company_name": "Amazon.com Inc.",
      "confidence_score": 56,
      "analysis": "\u26a1 Watch for confirmation with positive price action volume below average",
      "catalyst": "Alpha Vantage API data",
      "data_source": "alphavantage",
      "last_updated": "2025-12-22T06:31:03.396904",
      "region": "US"
    },
    {
      "ticker": "NFLX",
      "current_price": 94.39,
      "price_change": 0.39,
      "price_change_percent": 0.41,
      "volume": 78990153,
      "volume_ratio": 1.0,
      "company_name": "Netflix Inc.",
      "confidence_score": 56,
      "analysis": "\u26a1 Watch for confirmation with positive price action volume below average",
      "catalyst": "Alpha Vantage API data",
      "data_source": "alphavantage",
      "last_updated": "2025-12-22T06:31:05.773688",
      "region": "US"
    },
    {
      "ticker": "VOD.L",
      "current_price": 0.65,
      "price_change": -0.02,
      "price_change_percent": -2.59,
      "volume": 4027302,
      "volume_ratio": 0.88,
      "company_name": "Vodafone Group PLC",
      "confidence_score": 55,
      "analysis": "\u26a1 Watch for confirmation consolidating at current levels volume below average",
      "catalyst": "Sample data - API limited",
      "data_source": "sample",
      "last_updated": "2025-12-22T06:31:16.806433",
      "region": "UK"
    },
    {
      "ticker": "ASML.AS",
      "current_price": 719.89,
      "price_change": 11.83,
      "price_change_percent": 1.67,
      "volume": 28650246,
      "volume_ratio": 1.56,
      "company_name": "ASML Holding NV",
      "confidence_score": 55,
      "analysis": "\u26a1 Watch for confirmation with positive price action on high volume",
      "catalyst": "Sample data - API limited",
      "data_source": "sample",
      "last_updated": "2025-12-22T06:31:30.848987",
      "region": "EU"
    },
    {
      "ticker": "TSLA",
      "current_price": 481.2,
      "price_change": -2.17,
      "price_change_percent": -0.45,
      "volume": 103305424,
      "volume_ratio": 1.0,
      "company_name": "Tesla Inc.",
      "confidence_score": 50,
      "analysis": "\u26a1 Watch for confirmation consolidating at current levels volume below average",
      "catalyst": "Alpha Vantage API data",
      "data_source": "alphavantage",
      "last_updated": "2025-12-22T06:30:48.330683",
      "region": "US"
    },
    {
      "ticker": "META",
      "current_price": 658.77,
      "price_change": -5.68,
      "price_change_percent": -0.85,
      "volume": 49977051,
      "volume_ratio": 1.0,
      "company_name": "Meta Platforms Inc.",
      "confidence_score": 50,
      "analysis": "\u26a1 Watch for confirmation consolidating at current levels volume below average",
      "catalyst": "Alpha Vantage API data",
      "data_source": "alphavantage",
      "last_updated": "2025-12-22T06:31:00.149323",
      "region": "US"
    },
    {
      "ticker": "BMW.DE",
      "current_price": 100.65,
      "price_change": -2.44,
      "price_change_percent": -2.36,
      "volume": 23655097,
      "volume_ratio": 1.0,
      "company_name": "BMW AG",
      "confidence_score": 50,
      "analysis": "\u26a1 Watch for confirmation consolidating at current levels volume below average",
      "catalyst": "Sample data - API limited",
      "data_source": "sample",
      "last_updated": "2025-12-22T06:31:39.321943",
      "region": "EU"
    },
    {
      "ticker": "SIE.DE",
      "current_price": 177.26,
      "price_change": 7.15,
      "price_change_percent": 4.2,
      "volume": 29340283,
      "volume_ratio": 2.29,
      "company_name": "Siemens AG",
      "confidence_score": 47,
      "analysis": "\u26a1 Watch for confirmation with significant price movement on high volume",
      "catalyst": "Sample data - API limited",
      "data_source": "sample",
      "last_updated": "2025-12-22T06:31:26.109844",
      "region": "EU"
    }
  ]
}